demo_multiply/__init__.py
demo_multiply/multiplication.py
demo_multiply-0.7.0.dist-info/METADATA
demo_multiply-0.7.0.dist-info/WHEEL
demo_multiply-0.7.0.dist-info/top_level.txt
demo_multiply-0.7.0.dist-info/RECORD
