Metadata-Version: 2.1
Name: demo-multiply
Version: 0.7.0
Summary: Demo library
Home-page: 
Author: Saeed Anabtawi
Author-email: example@email.com
License: MIT
Classifier: Intended Audience :: Developers
Classifier: License :: OSI Approved :: MIT License
Classifier: Programming Language :: Python
Classifier: Programming Language :: Python :: 3.11
Classifier: Operating System :: OS Independent
